[{"text":"Для чего изначально создавался Java?","variants":["Для программирования роботов из будущего","Для интерактивного телевидения","Для того, чтобы стать лучшим языком программирования в мире","Для программирования мультиварок"],"rightAnswer":2},{"text":"Первое название Java – это..?","variants":["Coffee","Smalltalk","Coffee Tree","Oak"],"rightAnswer":4},{"text":"Кто разрабатывал Java?","variants":["Расс Кокс","Райан Гослинг","Джеймс Гослинг","Джеймс Кемерон"],"rightAnswer":3},{"text":"Самый популярный язык программирования в 2017 году – это..?","variants":["PHP","brainfuck","C","Java"],"rightAnswer":4},{"text":"Что должен носить с собой каждый программист по мнению Грейс Хоппер?","variants":["Щетку для соскребания жуков с перфокарт","Книгу по ассемблеру","Ожерелье длиной в микросекунду","Калькулятор"],"rightAnswer":3},{"text":"Какая из этих игр написана на Java?","variants":["Minecraft","Sims 2","World of Warcraft","Tetris"],"rightAnswer":1},{"text":"Как зовут пингвина, символ Linux?","variants":["Дюк","Фин","Толстячок","Такс"],"rightAnswer":4},{"text":"Язык программирования – предшественник языка С – это..?","variants":["B","C-C","N/C","Не было такого"],"rightAnswer":1},{"text":"Как изначально назывался язык С++?","variants":["C plus plus","всегда был С++","С с классами","С--"],"rightAnswer":3},{"text":"Backrub – это..?","variants":["Заклинание в Гарри Поттере","Первое название Google","Команда в C++","Название любимых конфет программистов"],"rightAnswer":2},{"text":"На чем был написана игра \"Тамагочи\"?","variants":["Java","C","Ассемблер","Python"],"rightAnswer":3},{"text":"Язык программирования Python назван в честь...","variants":["Сериала \"Летающий цирк Монти Пайтона\"","змеи – питона","напитка, который автор любил в детстве \"Python Long\"","фирмы кожзам изделий \"Python for everyone\""],"rightAnswer":1},{"text":"Первый в мире программист – это...","variants":["Бьерн Страуструп","Ада Августа Лавлейс","Деннис Ритчи","Ричард Столлман"],"rightAnswer":2},{"text":"Монада – это ...","variants":["мочеполовое заболевание","библиотека на JS","какая-то хрень в хаскеле","моноид в моноидальной категории эндофункторов"],"rightAnswer":4},{"text":"Почему символ Linux – пингвин..?","variants":["Остальные животные были заняты","Его просто нарисовать","Создателя в детстве укусил пингвин","у него тоже красные глаза"],"rightAnswer":3},{"text":"Для чего в PHP используется символ @ ?","variants":["Для красоты","Для морального успокоения","Для подавления ошибок","Не используется"],"rightAnswer":3},{"text":"Существуют PHP5, PHP7. Что с PHP6?","variants":["Он тоже существует","Ошибка в нумерации. Его пропустили случайно","Название ассоциировалось с уже существующими изменениями в языке","Обновление выпускали 6 июня 2006 года, не хотели выглядеть клоунами"],"rightAnswer":3},{"text":"Для чего использовалась первая веб-камера?","variants":["Чтобы следить за количеством кофе в кофеварке","Для прохождения интервью","Вместо сигнализации в доме","Чтобы смотреть за котейками"],"rightAnswer":1},{"text":"Почему Элтон Джон ненавидит интернет?","variants":["Из-за пиратской музыки","Из-за того, что бумажные письма почти вымерли, а он так их любил","Из-за того, что его расстраивают мемы о нем","Из-за интернета качество творчества падает"],"rightAnswer":4},{"text":"Что на эскимосском языке означает слово \"ikiaqqivik\"?","variants":["Программирование","Электронное письмо","Интернет","Facebook"],"rightAnswer":3},{"text":"Правильное название аэропорта калифорнийского города Сан-Карлос – это..?","variants":["SMS","MySQL","SQL","SDL"],"rightAnswer":3},{"text":"Откуда появилось название Oracle?","variants":["Это название любимого фильма создателя","Создатель очень любил ходить на игры любимой команды в Oracle Arena в Окленде","Это название проекта в ЦРУ, над которым раньше работал создатель Oracle","Его создателю предсказала гадалка за год до"],"rightAnswer":3},{"text":"Почему не существует первой версии Oracle?","variants":["Создатели боялись, что первая версия не заинтересует покупателей. И хотели обогнать конкурентов","Первая версия существовала","Гадалка нагадала, что V1 провалится","Создатели выпустили анонс в СМИ, но допустили ошибку в названии. Пришлось жить так"],"rightAnswer":1},{"text":"На чем была написана первая (по счету) версия Oracle?","variants":["Scala","Ada","Ассемблер","C"],"rightAnswer":3},{"text":"По словам разработчиков игры, для чего была создана Pokemon Go?","variants":["Чтобы собрать много денег","Помочь людям, страдающим от депрессии, тревоги и приступов паники","Чтобы возродить тему покемонов","Чтобы отпраздновать юбилей создания игры"],"rightAnswer":2},{"text":"Что такое Deep Learning?","variants":["Раздел на PornHub","Углубленная версия изучения любого языка программирования","Название музыкальной группы","Уровень технологий машинного обучения"],"rightAnswer":4},{"text":"Какая компания создала язык Go?","variants":["ВКонтакте","PornHub","Одноклассники","Google"],"rightAnswer":4},{"text":"Как называется IDE для программистов Go?","variants":["Go_","Go-Go","Gogland","GoWorld"],"rightAnswer":3},{"text":"Почему создатели Go исключили поддержку Try-Catch в языке?","variants":["Они не против try-catch, но пока не придумали, как правильно ее реализовать","Он провоцирует программиста на игнорирование ошибок","Хотели отличаться от Java и C++","Создатели считают что слишком большая вложенность – плохо"],"rightAnswer":2},{"text":"Кто создал первую вычислительную машину","variants":["Шеннон","Тесла","Тьюринг","Бэббидж"],"rightAnswer":4},{"text":"Способ, которым в компьютере обычно представлены целые числа со знаком","variants":["Прямой код","Кольцевой код","Обратный код","Дополнительный код"],"rightAnswer":4},{"text":"Песня Джонатана Коултона про программиста называется..?","variants":["Code Monkey","HardCode","It's raining code","Code or Die"],"rightAnswer":1},{"text":"Один символ в таблице ASCII занимает","variants":["16 бит","8 бит","32 бит","7 бит"],"rightAnswer":4},{"text":"Что необычного в языке Shakespeare?","variants":["маскирует исходный код программы под пьесы Шекспира","Его используют для создания и поддержки литературных сайтов","Код, написанный на этом языке, автоматически строит рифмы","Его придумал фанат Шекспира"],"rightAnswer":1},{"text":"Язык программирования, программы написанные на котором практически невозможно скомпилить?","variants":["С++","JavaScript","Befunge","ALGOL 68"],"rightAnswer":3},{"text":"Чем примечателен язык программирования WhiteSpace?","variants":["для управляющих конструкций используются только непечатаемые символы","Смысловую нагрузку несут только пробелы: количество их в последовательностях, а разделены они могут быть любыми другими знаками","Разметка только пробелами, при использовании табуляции программа не компилируется","Тем, что он не существует"],"rightAnswer":1},{"text":"Самый тонкий ноутбук в мире по версии Книги рекордов Гиннеса – это..?","variants":["HP Spectre","Dell Adamo XPS","MacBook Air","Asus ZenBook"],"rightAnswer":2},{"text":"Каким было самое большое расстояние между двумя компьютерами, которые удалось соединить по Wi-Fi?","variants":["400 метров","43 километра","88,6 километров","2,5 километров"],"rightAnswer":3},{"text":"Кто такой Канеюки Ямагучи?","variants":["Программист, проработавший на одном месте 49 лет","Инженер, создавший язык С","Единственный программист, работающий в PornHub","Программист, создавший первый браузер"],"rightAnswer":1},{"text":"Сколько бит в байте?","variants":["32","1","2","8"],"rightAnswer":4},{"text":"Первый ноутбук назывался...","variants":["Grid Compass 1100","Apple Lisa","IBM PC Convertible","Power Series Books"],"rightAnswer":1},{"text":"Как называется алгоритм, на котором работает поиск Google?","variants":["ТИЦ","PageRank","BigData","DataLake"],"rightAnswer":2},{"text":"Какой процессор появился раньше","variants":["Intel Celeron 266","Intel 8086","Intel 286","Intel Pentium 50"],"rightAnswer":2},{"text":"Что такое таблица виртуальных методов?","variants":["Таблица в памяти,\nкоторая используется \nв IDE для отображения\nподсказок","Такой таблицы не существует","Механизм, \nобеспечивающий работу\n с макросами в C++","механизм, используемый в языках программирования для поддержки динамического соответствия (или метода позднего связывания)"],"rightAnswer":4},{"text":"(не a) или (не b)","variants":["не (а или b)","(не a) или b","a или (не b)","не (a и b)"],"rightAnswer":4},{"text":"Обычно в Ethernet кабеле 5й категории проводов","variants":["4 пары","1 пара","8 пар","2 пары"],"rightAnswer":2},{"text":"Что значит слово ubuntu?","variants":["этикет","шайтан машина","человечность","порядок"],"rightAnswer":3},{"text":"Что лишнее?","variants":["Бегун","Ждун","Прыгун","Зомбак"],"rightAnswer":3},{"text":"Самый известный в мире алгоритм сжатия данных – это?","variants":["RLE","MP3","Pied Piper (Пегий Дудочник)","RTP (CRTP)"],"rightAnswer":3},{"text":"Что будет, если сложить по модулю 2 числа 10101 и 10101 ?","variants":["10001","20202","0","00001"],"rightAnswer":3},{"text":"Почему в Windows нельзя создать папку \"con\"","variants":["Из-за нарушения условий использования торговой марки CON LTD.","Это виртуальное устройство Windows - connection","Слово зарезервировано для обозначения I/O консоли","Гейтс не любил это слово, так как оно было его школьным прозвищем"],"rightAnswer":3},{"text":"Как некий Линус Торвальдс относится к NVidia?","variants":["Недолюбливает","Позитивно","Крайне негативно","Одобрительно"],"rightAnswer":3},{"text":"0 в Unix timestamp – это","variants":["1 января 1901г","1 января 0г","1 января 1970г","1 января 1900г"],"rightAnswer":3},{"text":"Когда было 1000000000?","variants":["9 февраля 1989","9 сентября 2001 года по UTC","1 января 1999","19 сентября 2002"],"rightAnswer":2},{"text":"Для чего официально предназначался 666 tcp/ip-порт?","variants":["DOOM","BBRP","MVTP","VCZP"],"rightAnswer":1},{"text":"Какого дистрибутива линукса не существовало?","variants":["DSL","Mandrake","Gebian","Knoppix"],"rightAnswer":3},{"text":"Метод масштабирования БД, заключающийся в разбиении крупных таблиц между несколькими серверами","variants":["Вертикальный шардинг","Диагональный шардинг","Горизонтальный шардинг","Всеобъемлющий шардинг"],"rightAnswer":3},{"text":"Какого уровня модели OSI не существует?","variants":["физический","логический","канальный","сетевой"],"rightAnswer":2},{"text":"Кто такой Страуструп?","variants":["ярый страусоненавистник","автор В","соавтор C","автор С++"],"rightAnswer":4},{"text":"Кто такой Расмус Лердорф?","variants":["ярый критик PHP","гражданин РФ","обычный датчанин","создатель PHP"],"rightAnswer":4},{"text":"ASCII-код для Enter / Carriage Return (CR)  в десятичной \nсистеме счисления","variants":["11","13","15","10"],"rightAnswer":2},{"text":"Самоконтролирующийся и самокорректирующийся код","variants":["код Хэмингуэя","код Шрёдингера","код да Винчи","код Хэмминга"],"rightAnswer":4},{"text":"Сколько бит в char?","variants":["12","1","8","4"],"rightAnswer":3},{"text":"Как сначала назывался язык С#?","variants":["C Sharp","C++++","C2","COOL"],"rightAnswer":4},{"text":"Компания, представившая миру язык C#, – это..?","variants":["C# создан сообществом","Google","Microsoft","Intel"],"rightAnswer":3},{"text":"Почему используется знак # в названии языка C#?","variants":["Чтобы добавить тюремной романтики","Нет никакого смысла","Потому что С и С++ были заняты","Это копия знака \"диез\""],"rightAnswer":4},{"text":"Один из самых известных компьютерных вирусов, начавший заражение с Филиппин, поразивший более 3 млн компьютеров","variants":["IINFECTYOU","IEATYOU","IHATEYOU","ILOVEYOU"],"rightAnswer":4},{"text":"Звук какого животного использован в антивирусе Касперского для оповещения о найденном вирусе?","variants":["Варана","Котика","Аллигатора","Свиньи"],"rightAnswer":4},{"text":"Самый старый компьютерный вирус – это..?","variants":["STALKER","Buddy","Creeper","Teddy Bear"],"rightAnswer":3},{"text":"Основной язык программирования в NASA?","variants":["JavaScript","Go","Assembler","С"],"rightAnswer":4},{"text":"Какой язык программирования использован NASA для визуальной навигации марсоходов?","variants":["JavaScript","Python","С++","Swift"],"rightAnswer":3},{"text":"Самый лучший язык программирования","variants":["C++","JavaScript","Java","PHP"],"rightAnswer":4},{"text":"Что из этого не является общепризнанным антипаттерном","variants":["Божественный объект","Полтергейст","Одиночка","Паблик Морозов"],"rightAnswer":3},{"text":"Какую функцию используют для реализации корутин?","variants":["sbrk","goto","coroutine_go","longjmp"],"rightAnswer":4},{"text":"Генетический алгоритм - это","variants":["Название непонятного куска в коде","Способ обучения нейронных сетей","Я на Баду! А ты?","Класс алгоритмов оптимизации"],"rightAnswer":4},{"text":"When I was six, my sister was half my age. Now I'm 70, how old is she?","variants":["67","38","6","35"],"rightAnswer":1},{"text":"Название языка PHP переводится как","variants":["Боже, только не Джава","Инструменты для создания персональных веб-страниц","Я не осилил Перл","Препроцессор гипертекста"],"rightAnswer":4},{"text":"Кем работал Александр Привалов до того как попасть в НИИЧАВО?","variants":["Астрономом","Программистом","Врачом","Водителем"],"rightAnswer":2},{"text":"В PHP если $a==$b и $b==$c, можно ли быть увереным, что $a==$c?","variants":["Не понял вопроса","Да","Не нужно писать на РНР","Нет"],"rightAnswer":4},{"text":"Сколько букв в русском алфавите","variants":["64","33","66","32"],"rightAnswer":2},{"text":"Чему равен 1 Кбит/с?","variants":["1024 бод","1000 бод","1024 бит/с","1000 бит/с"],"rightAnswer":4},{"text":"Сколько памяти \"хватит всем\"?","variants":["4 Гб","64 Кб","640 Кб","1 Мб"],"rightAnswer":3},{"text":"Перфокарты впервые начали применяться","variants":["в военной технике","в ткацких станках","в типографских станках","в БЭСМ"],"rightAnswer":2},{"text":"Закон Мура гласит о том, что...","variants":["производительность процессоров удваивается каждые 2 года","количество транзисторов в процессорах удваивается каждый год","количество транзисторов в процессорах удваивается каждые 2 года","Покупать новый iPhone каждый год — это глупо"],"rightAnswer":3},{"text":"В честь чего называется утилита ping","variants":["В честь пинг-понга","В честь звука, который издаёт сонар","В честь создателя из Китая по имени Чен Пинг","Probe Internal Network Grounds"],"rightAnswer":2},{"text":"Как называется балансировка средствами DNS","variants":["DNS Switch","Named","Round Robin","Robin Rabin"],"rightAnswer":3},{"text":"Что такое context switch?","variants":["Когда на всех сайтах в контекстной рекламе тебе начинают предлагать холодильники после посещения market.yandex.ru","Переключение интерпретатора языка из контекстно-зависимой грамматики в контекстно-независимую","Переключение процессора между задачами","Когда тебя постоянно отвлекают от работы менеджеры"],"rightAnswer":3},{"text":"echo \"Badoo123Bigger Than Dating\" | perl -nl -e '/^\\w(\\w)?.*?([A-Z]+).*?/ and print $2'","variants":["Bigger Than Dating","B","T","D"],"rightAnswer":2},{"text":"","variants":[null,null,null,null],"rightAnswer":1},{"text":"Что лишнее?","variants":["Pinba","libpssh","php-fpm","Nginx"],"rightAnswer":4},{"text":"Какое из этих сетевых устройств наиболее примитивно?","variants":["Концентратор (хаб)","Точка доступа","Коммутатор (свитч)","Маршрутизатор (роутер)"],"rightAnswer":1},{"text":"Чем известен Дональд Кнут?","variants":["Принимал пожертвования в размене 1 hexadecimal dollar ($2.56) на написание четвёртого тома","Написал трёхтомник \"искусство общения с менеджером\"","Тем, что его книги никто не читает","Проповедовал использование литературного английского в разработке"],"rightAnswer":3}]